EXAMPLES.rst
LICENSE
MANIFEST.in
README.rst
py3line.py
setup.py
py3line.egg-info/PKG-INFO
py3line.egg-info/SOURCES.txt
py3line.egg-info/dependency_links.txt
py3line.egg-info/entry_points.txt
py3line.egg-info/requires.txt
py3line.egg-info/top_level.txt